podbean_client.py
podbean_client-1.0.1.dist-info/DESCRIPTION.rst
podbean_client-1.0.1.dist-info/METADATA
podbean_client-1.0.1.dist-info/RECORD
podbean_client-1.0.1.dist-info/WHEEL
podbean_client-1.0.1.dist-info/metadata.json
podbean_client-1.0.1.dist-info/top_level.txt
